{
  "name": "client",
  "hash": "881b1da418b2463b73f5",
  "publicPath": "client/",
  "outputPath": "/home/runner/work/MyReact/MyReact/ui/ssr-example/dist/client",
  "assetsByChunkName": {
    "main": [
      "main-899432e8b2b128d5a9e0.css",
      "main-6866a603336b125521db.js"
    ],
    "runtime": [
      "runtime-a6fb7c04b0957e92a5db.js"
    ],
    "common-Layout": [
      "common-Layout-c78289379b380b855267.js"
    ],
    "pages-": [
      "pages--5d1e0aeb7cbbb2c59b5a.js"
    ],
    "pages-404": [
      "pages-404-6818f8f4c780a6598dbd.js"
    ],
    "pages-Blog": [
      "pages-Blog-2b5cd2e1bd3f9524ed23.js"
    ],
    "vendor-ui": [
      "vendor-ui-a90c72d63319fe52919e.js"
    ],
    "vendor-react": [
      "vendor-react-01f02022c65aa9cf7ad3.js"
    ],
    "vendor": [
      "vendor-90c5146cc6699a363406.css",
      "vendor-8e2cfc521f4fdb762d26.js"
    ],
    "vendor-babel": [
      "vendor-babel-28e1a2d9cf5548baed95.js"
    ],
    "vendor-lodash": [
      "vendor-lodash-0307fabf012c75cb3374.js"
    ]
  },
  "assets": [
    {
      "type": "asset",
      "name": "vendor-8e2cfc521f4fdb762d26.js",
      "size": 655883,
      "emitted": false,
      "comparedForEmit": false,
      "cached": true,
      "info": {
        "immutable": true,
        "contenthash": "8e2cfc521f4fdb762d26",
        "javascriptModule": false,
        "minimized": true,
        "related": {
          "license": "vendor-8e2cfc521f4fdb762d26.js.LICENSE.txt",
          "sourceMap": "vendor-8e2cfc521f4fdb762d26.js.map"
        }
      },
      "chunkNames": [
        "vendor"
      ],
      "chunkIdHints": [
        "vendor"
      ],
      "auxiliaryChunkNames": [],
      "auxiliaryChunkIdHints": [],
      "filteredRelated": 2,
      "chunks": [
        736
      ],
      "auxiliaryChunks": []
    },
    {
      "type": "asset",
      "name": "main-6866a603336b125521db.js",
      "size": 180195,
      "emitted": false,
      "comparedForEmit": false,
      "cached": true,
      "info": {
        "immutable": true,
        "contenthash": "6866a603336b125521db",
        "javascriptModule": false,
        "minimized": true,
        "related": {
          "sourceMap": "main-6866a603336b125521db.js.map"
        }
      },
      "chunkNames": [
        "main"
      ],
      "chunkIdHints": [],
      "auxiliaryChunkNames": [],
      "auxiliaryChunkIdHints": [],
      "filteredRelated": 1,
      "chunks": [
        179
      ],
      "auxiliaryChunks": []
    },
    {
      "type": "asset",
      "name": "vendor-ui-a90c72d63319fe52919e.js",
      "size": 166029,
      "emitted": false,
      "comparedForEmit": false,
      "cached": true,
      "info": {
        "immutable": true,
        "contenthash": "a90c72d63319fe52919e",
        "javascriptModule": false,
        "minimized": true,
        "related": {
          "sourceMap": "vendor-ui-a90c72d63319fe52919e.js.map"
        }
      },
      "chunkNames": [
        "vendor-ui"
      ],
      "chunkIdHints": [
        "vendor"
      ],
      "auxiliaryChunkNames": [],
      "auxiliaryChunkIdHints": [],
      "filteredRelated": 1,
      "chunks": [
        50
      ],
      "auxiliaryChunks": []
    },
    {
      "type": "asset",
      "name": "vendor-react-01f02022c65aa9cf7ad3.js",
      "size": 154566,
      "emitted": false,
      "comparedForEmit": false,
      "cached": true,
      "info": {
        "immutable": true,
        "contenthash": "01f02022c65aa9cf7ad3",
        "javascriptModule": false,
        "minimized": true,
        "related": {
          "license": "vendor-react-01f02022c65aa9cf7ad3.js.LICENSE.txt",
          "sourceMap": "vendor-react-01f02022c65aa9cf7ad3.js.map"
        }
      },
      "chunkNames": [
        "vendor-react"
      ],
      "chunkIdHints": [
        "vendor"
      ],
      "auxiliaryChunkNames": [],
      "auxiliaryChunkIdHints": [],
      "filteredRelated": 2,
      "chunks": [
        270
      ],
      "auxiliaryChunks": []
    },
    {
      "type": "asset",
      "name": "vendor-lodash-0307fabf012c75cb3374.js",
      "size": 42391,
      "emitted": false,
      "comparedForEmit": false,
      "cached": true,
      "info": {
        "immutable": true,
        "contenthash": "0307fabf012c75cb3374",
        "javascriptModule": false,
        "minimized": true,
        "related": {
          "sourceMap": "vendor-lodash-0307fabf012c75cb3374.js.map"
        }
      },
      "chunkNames": [
        "vendor-lodash"
      ],
      "chunkIdHints": [
        "vendor"
      ],
      "auxiliaryChunkNames": [],
      "auxiliaryChunkIdHints": [],
      "filteredRelated": 1,
      "chunks": [
        904
      ],
      "auxiliaryChunks": []
    },
    {
      "type": "asset",
      "name": "pages-Blog-2b5cd2e1bd3f9524ed23.js",
      "size": 38791,
      "emitted": false,
      "comparedForEmit": false,
      "cached": true,
      "info": {
        "immutable": true,
        "contenthash": "2b5cd2e1bd3f9524ed23",
        "javascriptModule": false,
        "minimized": true,
        "related": {
          "sourceMap": "pages-Blog-2b5cd2e1bd3f9524ed23.js.map"
        }
      },
      "chunkNames": [
        "pages-Blog"
      ],
      "chunkIdHints": [],
      "auxiliaryChunkNames": [],
      "auxiliaryChunkIdHints": [],
      "filteredRelated": 1,
      "chunks": [
        587
      ],
      "auxiliaryChunks": []
    },
    {
      "type": "asset",
      "name": "pages--5d1e0aeb7cbbb2c59b5a.js",
      "size": 27586,
      "emitted": false,
      "comparedForEmit": false,
      "cached": true,
      "info": {
        "immutable": true,
        "contenthash": "5d1e0aeb7cbbb2c59b5a",
        "javascriptModule": false,
        "minimized": true,
        "related": {
          "sourceMap": "pages--5d1e0aeb7cbbb2c59b5a.js.map"
        }
      },
      "chunkNames": [
        "pages-"
      ],
      "chunkIdHints": [],
      "auxiliaryChunkNames": [],
      "auxiliaryChunkIdHints": [],
      "filteredRelated": 1,
      "chunks": [
        617
      ],
      "auxiliaryChunks": []
    },
    {
      "type": "asset",
      "name": "vendor-babel-28e1a2d9cf5548baed95.js",
      "size": 14322,
      "emitted": false,
      "comparedForEmit": false,
      "cached": true,
      "info": {
        "immutable": true,
        "contenthash": "28e1a2d9cf5548baed95",
        "javascriptModule": false,
        "minimized": true,
        "related": {
          "license": "vendor-babel-28e1a2d9cf5548baed95.js.LICENSE.txt",
          "sourceMap": "vendor-babel-28e1a2d9cf5548baed95.js.map"
        }
      },
      "chunkNames": [
        "vendor-babel"
      ],
      "chunkIdHints": [
        "vendor"
      ],
      "auxiliaryChunkNames": [],
      "auxiliaryChunkIdHints": [],
      "filteredRelated": 2,
      "chunks": [
        89
      ],
      "auxiliaryChunks": []
    },
    {
      "type": "asset",
      "name": "common-Layout-c78289379b380b855267.js",
      "size": 14249,
      "emitted": false,
      "comparedForEmit": false,
      "cached": true,
      "info": {
        "immutable": true,
        "contenthash": "c78289379b380b855267",
        "javascriptModule": false,
        "minimized": true,
        "related": {
          "sourceMap": "common-Layout-c78289379b380b855267.js.map"
        }
      },
      "chunkNames": [
        "common-Layout"
      ],
      "chunkIdHints": [],
      "auxiliaryChunkNames": [],
      "auxiliaryChunkIdHints": [],
      "filteredRelated": 1,
      "chunks": [
        497
      ],
      "auxiliaryChunks": []
    },
    {
      "type": "asset",
      "name": "main-899432e8b2b128d5a9e0.css",
      "size": 4322,
      "emitted": false,
      "comparedForEmit": false,
      "cached": true,
      "info": {
        "immutable": true,
        "contenthash": "899432e8b2b128d5a9e0",
        "minimized": true,
        "related": {
          "sourceMap": "main-899432e8b2b128d5a9e0.css.map"
        }
      },
      "chunkNames": [
        "main"
      ],
      "chunkIdHints": [],
      "auxiliaryChunkNames": [],
      "auxiliaryChunkIdHints": [],
      "filteredRelated": 1,
      "chunks": [
        179
      ],
      "auxiliaryChunks": []
    },
    {
      "type": "asset",
      "name": "runtime-a6fb7c04b0957e92a5db.js",
      "size": 3466,
      "emitted": false,
      "comparedForEmit": false,
      "cached": true,
      "info": {
        "immutable": true,
        "contenthash": "a6fb7c04b0957e92a5db",
        "javascriptModule": false,
        "minimized": true,
        "related": {
          "sourceMap": "runtime-a6fb7c04b0957e92a5db.js.map"
        }
      },
      "chunkNames": [
        "runtime"
      ],
      "chunkIdHints": [],
      "auxiliaryChunkNames": [],
      "auxiliaryChunkIdHints": [],
      "filteredRelated": 1,
      "chunks": [
        666
      ],
      "auxiliaryChunks": []
    },
    {
      "type": "asset",
      "name": "vendor-90c5146cc6699a363406.css",
      "size": 3414,
      "emitted": false,
      "comparedForEmit": false,
      "cached": true,
      "info": {
        "immutable": true,
        "contenthash": "90c5146cc6699a363406",
        "minimized": true,
        "related": {
          "sourceMap": "vendor-90c5146cc6699a363406.css.map"
        }
      },
      "chunkNames": [
        "vendor"
      ],
      "chunkIdHints": [
        "vendor"
      ],
      "auxiliaryChunkNames": [],
      "auxiliaryChunkIdHints": [],
      "filteredRelated": 1,
      "chunks": [
        736
      ],
      "auxiliaryChunks": []
    },
    {
      "type": "asset",
      "name": "pages-404-6818f8f4c780a6598dbd.js",
      "size": 493,
      "emitted": false,
      "comparedForEmit": false,
      "cached": true,
      "info": {
        "immutable": true,
        "contenthash": "6818f8f4c780a6598dbd",
        "javascriptModule": false,
        "minimized": true,
        "related": {
          "sourceMap": "pages-404-6818f8f4c780a6598dbd.js.map"
        }
      },
      "chunkNames": [
        "pages-404"
      ],
      "chunkIdHints": [],
      "auxiliaryChunkNames": [],
      "auxiliaryChunkIdHints": [],
      "filteredRelated": 1,
      "chunks": [
        751
      ],
      "auxiliaryChunks": []
    },
    {
      "type": "asset",
      "name": "manifest-deps.json",
      "size": 235,
      "emitted": false,
      "comparedForEmit": false,
      "cached": true,
      "info": {},
      "chunkNames": [],
      "chunkIdHints": [],
      "auxiliaryChunkNames": [],
      "auxiliaryChunkIdHints": [],
      "chunks": [],
      "auxiliaryChunks": []
    }
  ],
  "namedChunkGroups": {
    "main": {
      "name": "main",
      "chunks": [
        666,
        50,
        270,
        736,
        89,
        904,
        179
      ],
      "assets": [
        {
          "name": "runtime-a6fb7c04b0957e92a5db.js"
        },
        {
          "name": "vendor-ui-a90c72d63319fe52919e.js"
        },
        {
          "name": "vendor-react-01f02022c65aa9cf7ad3.js"
        },
        {
          "name": "vendor-90c5146cc6699a363406.css"
        },
        {
          "name": "vendor-8e2cfc521f4fdb762d26.js"
        },
        {
          "name": "vendor-babel-28e1a2d9cf5548baed95.js"
        },
        {
          "name": "vendor-lodash-0307fabf012c75cb3374.js"
        },
        {
          "name": "main-899432e8b2b128d5a9e0.css"
        },
        {
          "name": "main-6866a603336b125521db.js"
        }
      ],
      "filteredAssets": 0,
      "assetsSize": null,
      "filteredAuxiliaryAssets": 9,
      "auxiliaryAssetsSize": null,
      "children": {},
      "childAssets": {}
    },
    "common-Layout": {
      "name": "common-Layout",
      "chunks": [
        50,
        270,
        736,
        89,
        497
      ],
      "assets": [
        {
          "name": "vendor-ui-a90c72d63319fe52919e.js"
        },
        {
          "name": "vendor-react-01f02022c65aa9cf7ad3.js"
        },
        {
          "name": "vendor-90c5146cc6699a363406.css"
        },
        {
          "name": "vendor-8e2cfc521f4fdb762d26.js"
        },
        {
          "name": "vendor-babel-28e1a2d9cf5548baed95.js"
        },
        {
          "name": "common-Layout-c78289379b380b855267.js"
        }
      ],
      "filteredAssets": 0,
      "assetsSize": null,
      "filteredAuxiliaryAssets": 6,
      "auxiliaryAssetsSize": null,
      "children": {},
      "childAssets": {}
    },
    "pages-": {
      "name": "pages-",
      "chunks": [
        50,
        270,
        736,
        89,
        904,
        617
      ],
      "assets": [
        {
          "name": "vendor-ui-a90c72d63319fe52919e.js"
        },
        {
          "name": "vendor-react-01f02022c65aa9cf7ad3.js"
        },
        {
          "name": "vendor-90c5146cc6699a363406.css"
        },
        {
          "name": "vendor-8e2cfc521f4fdb762d26.js"
        },
        {
          "name": "vendor-babel-28e1a2d9cf5548baed95.js"
        },
        {
          "name": "vendor-lodash-0307fabf012c75cb3374.js"
        },
        {
          "name": "pages--5d1e0aeb7cbbb2c59b5a.js"
        }
      ],
      "filteredAssets": 0,
      "assetsSize": null,
      "filteredAuxiliaryAssets": 7,
      "auxiliaryAssetsSize": null,
      "children": {},
      "childAssets": {}
    },
    "pages-404": {
      "name": "pages-404",
      "chunks": [
        50,
        751
      ],
      "assets": [
        {
          "name": "vendor-ui-a90c72d63319fe52919e.js"
        },
        {
          "name": "pages-404-6818f8f4c780a6598dbd.js"
        }
      ],
      "filteredAssets": 0,
      "assetsSize": null,
      "filteredAuxiliaryAssets": 2,
      "auxiliaryAssetsSize": null,
      "children": {},
      "childAssets": {}
    },
    "pages-404-tsx": {
      "name": "pages-404-tsx",
      "chunks": [
        50,
        751
      ],
      "assets": [
        {
          "name": "vendor-ui-a90c72d63319fe52919e.js"
        },
        {
          "name": "pages-404-6818f8f4c780a6598dbd.js"
        }
      ],
      "filteredAssets": 0,
      "assetsSize": null,
      "filteredAuxiliaryAssets": 2,
      "auxiliaryAssetsSize": null,
      "children": {},
      "childAssets": {}
    },
    "pages-Blog": {
      "name": "pages-Blog",
      "chunks": [
        50,
        270,
        736,
        89,
        904,
        587
      ],
      "assets": [
        {
          "name": "vendor-ui-a90c72d63319fe52919e.js"
        },
        {
          "name": "vendor-react-01f02022c65aa9cf7ad3.js"
        },
        {
          "name": "vendor-90c5146cc6699a363406.css"
        },
        {
          "name": "vendor-8e2cfc521f4fdb762d26.js"
        },
        {
          "name": "vendor-babel-28e1a2d9cf5548baed95.js"
        },
        {
          "name": "vendor-lodash-0307fabf012c75cb3374.js"
        },
        {
          "name": "pages-Blog-2b5cd2e1bd3f9524ed23.js"
        }
      ],
      "filteredAssets": 0,
      "assetsSize": null,
      "filteredAuxiliaryAssets": 7,
      "auxiliaryAssetsSize": null,
      "children": {},
      "childAssets": {}
    },
    "pages-Blog-tsx": {
      "name": "pages-Blog-tsx",
      "chunks": [
        50,
        270,
        736,
        89,
        904,
        587
      ],
      "assets": [
        {
          "name": "vendor-ui-a90c72d63319fe52919e.js"
        },
        {
          "name": "vendor-react-01f02022c65aa9cf7ad3.js"
        },
        {
          "name": "vendor-90c5146cc6699a363406.css"
        },
        {
          "name": "vendor-8e2cfc521f4fdb762d26.js"
        },
        {
          "name": "vendor-babel-28e1a2d9cf5548baed95.js"
        },
        {
          "name": "vendor-lodash-0307fabf012c75cb3374.js"
        },
        {
          "name": "pages-Blog-2b5cd2e1bd3f9524ed23.js"
        }
      ],
      "filteredAssets": 0,
      "assetsSize": null,
      "filteredAuxiliaryAssets": 7,
      "auxiliaryAssetsSize": null,
      "children": {},
      "childAssets": {}
    },
    "pages-index": {
      "name": "pages-index",
      "chunks": [
        50,
        270,
        736,
        89,
        904,
        617
      ],
      "assets": [
        {
          "name": "vendor-ui-a90c72d63319fe52919e.js"
        },
        {
          "name": "vendor-react-01f02022c65aa9cf7ad3.js"
        },
        {
          "name": "vendor-90c5146cc6699a363406.css"
        },
        {
          "name": "vendor-8e2cfc521f4fdb762d26.js"
        },
        {
          "name": "vendor-babel-28e1a2d9cf5548baed95.js"
        },
        {
          "name": "vendor-lodash-0307fabf012c75cb3374.js"
        },
        {
          "name": "pages--5d1e0aeb7cbbb2c59b5a.js"
        }
      ],
      "filteredAssets": 0,
      "assetsSize": null,
      "filteredAuxiliaryAssets": 7,
      "auxiliaryAssetsSize": null,
      "children": {},
      "childAssets": {}
    },
    "pages-index-tsx": {
      "name": "pages-index-tsx",
      "chunks": [
        50,
        270,
        736,
        89,
        904,
        617
      ],
      "assets": [
        {
          "name": "vendor-ui-a90c72d63319fe52919e.js"
        },
        {
          "name": "vendor-react-01f02022c65aa9cf7ad3.js"
        },
        {
          "name": "vendor-90c5146cc6699a363406.css"
        },
        {
          "name": "vendor-8e2cfc521f4fdb762d26.js"
        },
        {
          "name": "vendor-babel-28e1a2d9cf5548baed95.js"
        },
        {
          "name": "vendor-lodash-0307fabf012c75cb3374.js"
        },
        {
          "name": "pages--5d1e0aeb7cbbb2c59b5a.js"
        }
      ],
      "filteredAssets": 0,
      "assetsSize": null,
      "filteredAuxiliaryAssets": 7,
      "auxiliaryAssetsSize": null,
      "children": {},
      "childAssets": {}
    }
  },
  "generator": "loadable-components",
  "chunks": [
    {
      "id": 179,
      "files": [
        "main-899432e8b2b128d5a9e0.css",
        "main-6866a603336b125521db.js"
      ]
    },
    {
      "id": 666,
      "files": [
        "runtime-a6fb7c04b0957e92a5db.js"
      ]
    },
    {
      "id": 497,
      "files": [
        "common-Layout-c78289379b380b855267.js"
      ]
    },
    {
      "id": 617,
      "files": [
        "pages--5d1e0aeb7cbbb2c59b5a.js"
      ]
    },
    {
      "id": 751,
      "files": [
        "pages-404-6818f8f4c780a6598dbd.js"
      ]
    },
    {
      "id": 587,
      "files": [
        "pages-Blog-2b5cd2e1bd3f9524ed23.js"
      ]
    },
    {
      "id": 50,
      "files": [
        "vendor-ui-a90c72d63319fe52919e.js"
      ]
    },
    {
      "id": 270,
      "files": [
        "vendor-react-01f02022c65aa9cf7ad3.js"
      ]
    },
    {
      "id": 736,
      "files": [
        "vendor-90c5146cc6699a363406.css",
        "vendor-8e2cfc521f4fdb762d26.js"
      ]
    },
    {
      "id": 89,
      "files": [
        "vendor-babel-28e1a2d9cf5548baed95.js"
      ]
    },
    {
      "id": 904,
      "files": [
        "vendor-lodash-0307fabf012c75cb3374.js"
      ]
    }
  ]
}